blessable/__init__.py
blessable/blessable.py
blessable/colormap.py
blessable-1.1.1.dist-info/METADATA
blessable-1.1.1.dist-info/WHEEL
blessable-1.1.1.dist-info/top_level.txt
blessable-1.1.1.dist-info/RECORD
