Metadata-Version: 2.1
Name: blessable
Version: 1.1.1
Summary: "Blessable" - a simple markup language for Blessings.
Home-page: https://github.com/fakerybakery/blessable
Author: www.mrfake.name
Project-URL: Bug Reports, https://github.com/fakerybakery/blessable/issues
Project-URL: Source, https://github.com/fakerybakery/blessable
Requires-Dist: blessed
